etc/file_dir_backup.cfg
file_dir_backup/__init__.py
file_dir_backup/__main__.py
file_dir_backup/cli.py
file_dir_backup/constants.py
file_dir_backup/core.py
file_dir_backup/logger.py
tests/__init__.py
tests/test_file_dir_backup.py
file_dir_backup-0.1.4.dist-info/AUTHORS
file_dir_backup-0.1.4.dist-info/METADATA
file_dir_backup-0.1.4.dist-info/WHEEL
file_dir_backup-0.1.4.dist-info/entry_points.txt
file_dir_backup-0.1.4.dist-info/top_level.txt
file_dir_backup-0.1.4.dist-info/RECORD
