Metadata-Version: 2.1
Name: file-dir-backup
Version: 0.1.4
Summary: A file and directory backup tool
Home-page: https://github.com/hujianli94/file_dir_backup
Author: hjl
Author-email: 1878324764@qq.com
License: MIT
Keywords: backup file directory rsync
Platform: UNKNOWN
Classifier: License :: OSI Approved :: MIT License
Classifier: Operating System :: OS Independent
Classifier: Topic :: System :: Archiving :: Backup
Classifier: Topic :: Utilities
Classifier: Programming Language :: Python :: 3
Classifier: Programming Language :: Python :: 3.8
Classifier: Programming Language :: Python :: 3.9
Classifier: Programming Language :: Python :: 3.10
Classifier: Programming Language :: Python :: 3.11
Requires-Python: >=3.6
